assis/__init__.py
assis/files_man.py
assis/main.py
assis/utils.py
assis/local_openia/__init__.py
assis/local_openia/main.py
assis/local_openia/utils.py
assis/local_openia/statement/__init__.py
assis/local_openia/statement/main.yaml
assis-0.3.2.dist-info/LICENSE.txt
assis-0.3.2.dist-info/METADATA
assis-0.3.2.dist-info/WHEEL
assis-0.3.2.dist-info/entry_points.txt
assis-0.3.2.dist-info/top_level.txt
assis-0.3.2.dist-info/RECORD
