Metadata-Version: 2.1
Name: assis
Version: 0.3.2
Summary: A doc generator for data engineering projects.
Home-page: https://github.com/pedrohgoncalvess/assis
Author: Pedro H. Gonçalves
Author-email: pedro_gonsalves@hotmail.com
Requires-Python: >=3.6
License-File: LICENSE.txt
Requires-Dist: openai
Requires-Dist: python-dotenv
Requires-Dist: pyyaml
